nts/__init__.py
nts/__main__.py
nts/__version__.py
nts/nts.py
nts_dgraham-1.3.3.dist-info/LICENSE
nts_dgraham-1.3.3.dist-info/METADATA
nts_dgraham-1.3.3.dist-info/WHEEL
nts_dgraham-1.3.3.dist-info/entry_points.txt
nts_dgraham-1.3.3.dist-info/top_level.txt
nts_dgraham-1.3.3.dist-info/RECORD
